LICENSE.txt
MANIFEST.in
README.md
WebServerIdentifier.py
requirements.txt
setup.py
WebServerIdentifier.egg-info/PKG-INFO
WebServerIdentifier.egg-info/SOURCES.txt
WebServerIdentifier.egg-info/dependency_links.txt
WebServerIdentifier.egg-info/entry_points.txt
WebServerIdentifier.egg-info/requires.txt
WebServerIdentifier.egg-info/top_level.txt