Metadata-Version: 2.1
Name: WebServerIdentifier
Version: 0.0.1
Summary: This package identifies Web servers using an aggressive technique based on the maximum size of the URI.
Home-page: https://github.com/mauricelambert/WebServerIdentifier
Author: Maurice Lambert
Author-email: mauricelambert434@gmail.com
Maintainer: Maurice Lambert
Maintainer-email: mauricelambert434@gmail.com
License: GPL-3.0 License
Project-URL: Documentation, https://mauricelambert.github.io/info/python/security/WebServerIdentifier.html
Project-URL: Executable, https://mauricelambert.github.io/info/python/security/WebServerIdentifier.pyz
Keywords: ARP,arpcachepoisonning,arpcachepoison,network,ManInTheMiddle,MIM,Security,DoS,DenialOfService
Platform: Windows
Platform: Linux
Platform: MacOS
Classifier: Programming Language :: Python
Classifier: Development Status :: 5 - Production/Stable
Classifier: Environment :: Web Environment
Classifier: Environment :: Console
Classifier: Topic :: Security
Classifier: Topic :: Internet :: WWW/HTTP :: HTTP Servers
Classifier: Natural Language :: English
Classifier: Programming Language :: Python :: 3.9
Classifier: Operating System :: POSIX :: Linux
Classifier: Operating System :: Microsoft :: Windows
Classifier: Operating System :: MacOS
Requires-Python: >=3.6
License-File: LICENSE.txt
